[
  {
    "id": "c1-intro",
    "type": "big-notes",
    "title": "Concept No. 1: The 'One Of' Rule 👑",
    "content": {
      "heading": "The Group Selection Rule",
      "body": "<p><strong>One of, Everyone of, A group of, Either of, Each of, Each one of, A flock of, A pair of, A herd of</strong> तथा <strong>Neither of</strong> के बाद noun or pronoun 'Plural' तथा Verb 'Singular' आता है। verb के बाद आने वाला pronoun हमेशा singular (his/her) आता है!</p>",
      "highlights": [
        "Noun/Pronoun MUST be Plural",
        "Verb MUST be Singular",
        "Following Pronoun MUST be Singular (his/her)"
      ]
    },
    "themeId": "emerald"
  },
  {
    "id": "c1-jugad",
    "type": "analogy-box",
    "title": "देशी जुगाड़ Method 🧠",
    "content": {
      "concept": "Plural Noun + Singular Verb का असली Logic",
      "analogy": "एक निकालने के लिए, एक से ज्यादा चाहिए!",
      "explanation": "इस नियम को रटने की जरूरत नहीं है। अगर आपको 'One' निकालना है, तो आप 1 में से 1 नहीं निकाल सकते। इसके लिए हमें एक से ज्यादा की जरूरत है, मतलब Noun/Pronoun <strong>'Plural'</strong> आएगा। और क्योंकि हम बात सिर्फ 'One' की कर रहे हैं, तो Verb <strong>'Singular'</strong> ही आएगी।"
    },
    "themeId": "violet"
  },
  {
    "id": "c1-pattern",
    "type": "pattern-box",
    "title": "Golden Structure ✨",
    "content": {
      "pattern": "[One of...] + [Plural Noun] + [Singular Verb]",
      "examples": [
        "Selection Word: One of, Each of, Neither of, etc.",
        "Noun: MUST be Plural (boxes, brothers)",
        "Verb: MUST be Singular (is, has, writes)"
      ],
      "rule": 
        "Noun/Pronoun MUST be Plural and Verb MUST be Singular. Following Pronoun MUST be Singular (his/her)."
      
    },
    "themeId": "indigo"
  },
  {
    "id": "c1-warning",
    "type": "warning-box",
    "title": "Exam वाली गलती 🚨",
    "content": {
      "message": "एग्जाम में ज्यादातर Verb और Plural 'Noun /Pronoun' वाली गलती होती है। Examiner या तो Noun को Singularकर देगा, या Verb को Plural कर देगा।",
      "severity": "high",
      "icon": "🚨"
    },
    "themeId": "ruby"
  },
  {
    "id": "c1-examples",
    "type": "big-notes",
    "title": "Lock these in your brain 📚",
    "content": {
      "heading": "Exam Frequent Sentences",
      "body": "<ul><li>One of his brothers <strong>is</strong> a teacher.</li><li>Everyone of the boys <strong>likes</strong> to ride.</li><li>Either of them <strong>has</strong> forgotten <strong>his</strong> umbrella.</li><li>Neither of his daughters <strong>is</strong> married.</li><li>A group of my friends <strong>wants</strong> to visit the new plant.</li></ul>"
    },
    "themeId": "slate-2"
  },
  {
    "id": "c1-rw",
    "type": "right-wrong",
    "title": "Spot the Error (PYQ Traps) 👁️",
    "content": {
      "statements": [
        {
          "id": "s1",
          "statement": "Land revenue was one of the major source of income.",
          "isCorrect": false,
          "explanation": "❌ False. Noun must be plural: major <strong>sources</strong>."
        },
        {
          "id": "s2",
          "statement": "One of my brothers writes novels for leisure.",
          "isCorrect": true,
          "explanation": "✅ True. Plural noun (brothers) + Singular verb (writes)."
        },
        {
          "id": "s3",
          "statement": "One of these boxes have the portrait of the heiress.",
          "isCorrect": false,
          "explanation": "❌ False. Verb must be singular: <strong>has</strong>."
        }
      ]
    },
    "themeId": "coral"
  }
]